plapperkasten/__init__.py
plapperkasten/config.py
plapperkasten/event.py
plapperkasten/eventmap.py
plapperkasten/keymap.py
plapperkasten/plapperkasten.py
plapperkasten/plugin.py
plapperkasten/plklogging/__init__.py
plapperkasten/plklogging/plklogging.py
plapperkasten/plugins/autoshutdown/autoshutdown.py
plapperkasten/plugins/autoshutdown/config.yaml
plapperkasten/plugins/espeak/config.yaml
plapperkasten/plugins/espeak/espeak.py
plapperkasten/plugins/example/config.yaml
plapperkasten/plugins/example/example.py
plapperkasten/plugins/inputdevinputevent/config.yaml
plapperkasten/plugins/inputdevinputevent/inputdevinputevent.py
plapperkasten/plugins/inputgpiod/config.yaml
plapperkasten/plugins/inputgpiod/inputgpiod.py
plapperkasten/plugins/inputnamedpipe/config.yaml
plapperkasten/plugins/inputnamedpipe/inputnamedpipe.py
plapperkasten/plugins/mpdclient/__init__.py
plapperkasten/plugins/mpdclient/config.yaml
plapperkasten/plugins/mpdclient/mpdclient.py
plapperkasten/plugins/mpdclient/statusmap.py
plapperkasten/plugins/server/config.yaml
plapperkasten/plugins/server/plkserver.py
plapperkasten/plugins/server/server.py
plapperkasten/plugins/server/templates/directory.html
plapperkasten/plugins/server/templates/display_main.html
plapperkasten/plugins/server/templates/error.html
plapperkasten/plugins/server/www/favicon.ico
plapperkasten/plugins/server/www/index.html
plapperkasten/plugins/server/www/normalize.css
plapperkasten/plugins/server/www/style.css
plapperkasten/plugins/soundalsa/__init__.py
plapperkasten/plugins/soundalsa/config.yaml
plapperkasten/plugins/soundalsa/soundalsa.py
plapperkasten/plugins/soundalsa/statusmap.py
plapperkasten/plugins/soundeffects/config.yaml
plapperkasten/plugins/soundeffects/soundeffects.py
plapperkasten/plugins/soundeffects/sounds/144319__fumiya112__decide.wav
plapperkasten/plugins/soundeffects/sounds/273925__lemonjolly__hooray-yeah.wav
plapperkasten/plugins/soundeffects/sounds/331381__qubodup__public-domain-jump-sound.wav
plapperkasten-0.8.8.dist-info/LICENSE
plapperkasten-0.8.8.dist-info/METADATA
plapperkasten-0.8.8.dist-info/WHEEL
plapperkasten-0.8.8.dist-info/entry_points.txt
plapperkasten-0.8.8.dist-info/top_level.txt
plapperkasten-0.8.8.dist-info/RECORD
