Metadata-Version: 2.1
Name: plapperkasten
Version: 0.8.8
Author-email: Eike Kühn <eike.kuehn@pixelwoelkchen.de>
Maintainer-email: Eike Kühn <eike.kuehn@pixelwoelkchen.de>
Project-URL: homepage, https://github.com/randomchars42/plapperkasten
Project-URL: documentation, https://github.com/randomchars42/plapperkasten
Project-URL: source, https://github.com/randomchars42/plapperkasten
Project-URL: tracker, https://github.com/randomchars42/plapperkasten/issues
Classifier: License :: OSI Approved :: The Unlicense (Unlicense)
Classifier: Programming Language :: Python :: 3
Classifier: Programming Language :: Python :: 3.9
Classifier: Programming Language :: Python :: 3.10
Classifier: Programming Language :: Python :: 3 :: Only
Classifier: Development Status :: 5 - Production/Stable
Classifier: Programming Language :: Python
Requires-Python: >=3.9
License-File: LICENSE
Requires-Dist: pyyaml (~=6.0)
Requires-Dist: evdev (~=1.4.0)
Requires-Dist: python-mpd2 (~=3.0.5)
Requires-Dist: plapperkastenserver (~=0.3.0)
Provides-Extra: inputgpiod
Requires-Dist: gpiodmonitor (~=1.3.1) ; extra == 'inputgpiod'
